[
  {
    "問題文": "He must be tired after such a long flight. この must の意味として最も適切なものはどれか。",
    "選択肢": [
      "〜にちがいない",
      "〜しなければならない",
      "〜かもしれない"
    ],
    "正解": 1,
    "解説": "状態を表す be とともに使う must は強い推量「〜にちがいない」。義務「〜しなければならない」と文脈で見分ける。"
  },
  {
    "問題文": "You must submit the application by Friday. この must の意味として最も適切なものはどれか。",
    "選択肢": [
      "〜にちがいない",
      "〜しなければならない",
      "〜した方がよい"
    ],
    "正解": 2,
    "解説": "submit のような動作動詞＋期限の文脈では must は義務「〜しなければならない」。推量の must との区別が問われる。"
  },
  {
    "問題文": "She must have left already; the lights are off. この must have left の意味として最も適切なものはどれか。",
    "選択肢": [
      "出るべきだった",
      "出たかもしれない",
      "出たにちがいない"
    ],
    "正解": 3,
    "解説": "must have p.p. は過去のことへの強い推量「〜したにちがいない」。should have（すべきだった）や may have（したかもしれない）と区別する。"
  },
  {
    "問題文": "He cannot have said such a rude thing. この cannot have said の意味として最も適切なものはどれか。",
    "選択肢": [
      "言ったはずがない",
      "言ってはいけなかった",
      "言う必要はなかった"
    ],
    "正解": 1,
    "解説": "cannot have p.p. は過去のことへの否定の推量「〜したはずがない」。must have の反対にあたる強い打ち消し。"
  },
  {
    "問題文": "You should have told me about it earlier. この should have told の意味として最も適切なものはどれか。",
    "選択肢": [
      "もっと早く言ったにちがいない",
      "もっと早く言うべきだった（のに言わなかった）",
      "もっと早く言う必要はなかった"
    ],
    "正解": 2,
    "解説": "should have p.p. は「〜すべきだったのに（しなかった）」という後悔・非難。実際にはしなかったことを含意する。"
  },
  {
    "問題文": "You need not have hurried; there was plenty of time. この need not have hurried の意味として最も適切なものはどれか。",
    "選択肢": [
      "急ぐべきだった",
      "急いだはずがない",
      "急ぐ必要はなかった（のに急いだ）"
    ],
    "正解": 3,
    "解説": "need not have p.p. は「〜する必要はなかったのに（実際はした）」。無駄な行為をしたことを表す。"
  },
  {
    "問題文": "She may have missed the last train. この may have missed の意味として最も適切なものはどれか。",
    "選択肢": [
      "乗り遅れたかもしれない",
      "乗り遅れたにちがいない",
      "乗り遅れるべきだった"
    ],
    "正解": 1,
    "解説": "may have p.p. は過去のことへの弱い推量「〜したかもしれない」。確信の強い must have（したにちがいない）と区別する。"
  },
  {
    "問題文": "It could be true, but I am not certain. この could の意味として最も適切なものはどれか。",
    "選択肢": [
      "〜のはずがない",
      "〜かもしれない",
      "かつて〜できた"
    ],
    "正解": 2,
    "解説": "ここでの could は現在の可能性「〜かもしれない」。過去の能力「〜できた」ではなく、推量の用法。"
  },
  {
    "問題文": "The door would not open however hard I pushed. この would not open の意味として最も適切なものはどれか。",
    "選択肢": [
      "開くべきでなかった",
      "開く予定ではなかった",
      "どうしても開かなかった"
    ],
    "正解": 3,
    "解説": "否定の would not は「どうしても〜しようとしなかった」という拒絶・固執。物事が主語でも「どうしても〜しなかった」と訳す。"
  },
  {
    "問題文": "You had better see a doctor right away. この had better の意味として最も適切なものはどれか。",
    "選択肢": [
      "〜した方がよい（さもないと困る）",
      "〜したいものだ",
      "〜だったらよかったのに"
    ],
    "正解": 1,
    "解説": "had better は「〜した方がよい」という強めの助言・警告で、従わないと良くない含みがある。願望や仮定の意味ではない。"
  },
  {
    "問題文": "I would rather stay home ___ go out tonight. 空所に最も適切な語はどれか。",
    "選択肢": [
      "to",
      "than",
      "rather"
    ],
    "正解": 2,
    "解説": "would rather A than B で「BよりむしろAしたい」。A・B には動詞の原形が入り、結ぶのは than。"
  },
  {
    "問題文": "She may well be angry about the sudden change. この may well の意味として最も適切なものはどれか。",
    "選択肢": [
      "うまく怒ることができる",
      "おそらく怒らないだろう",
      "怒るのももっともだ・当然怒るだろう"
    ],
    "正解": 3,
    "解説": "may well は「〜するのももっともだ／たぶん〜だろう」。well を「うまく」と直訳せず、妥当性・高い可能性を表す。"
  },
  {
    "問題文": "We may as well start now since everyone is here. この may as well の意味として最も適切なものはどれか。",
    "選択肢": [
      "今始めた方がよい",
      "今始めることができる",
      "今始めたいにちがいない"
    ],
    "正解": 1,
    "解説": "may as well は「（どうせなら）〜した方がよい」という消極的な提案。他に良い選択肢がない状況で使う。"
  },
  {
    "問題文": "You cannot be ___ careful when crossing this busy street. 空所に最も適切な語はどれか。",
    "選択肢": [
      "very",
      "too",
      "so"
    ],
    "正解": 2,
    "解説": "cannot ... too は「いくら〜してもしすぎることはない」という強い勧め。too 以外の very や so ではこの慣用の意味にならない。"
  },
  {
    "問題文": "You ought to apologize to her for the mistake. この ought to の意味として最も適切なものはどれか。",
    "選択肢": [
      "〜したにちがいない",
      "〜したい",
      "〜すべきだ"
    ],
    "正解": 3,
    "解説": "ought to は should とほぼ同義で「〜すべきだ」という義務・当然。推量や願望の意味ではない。"
  },
  {
    "問題文": "The ceremony is to be held next Sunday. この is to の意味として最も適切なものはどれか。",
    "選択肢": [
      "開かれる予定だ",
      "開かれたがっている",
      "開かれたにちがいない"
    ],
    "正解": 1,
    "解説": "be to do は文脈により予定・義務・運命などを表す。ここでは「〜する予定だ」という予定の用法。"
  },
  {
    "問題文": "You need not worry about the result so much. この need not の意味として最も適切なものはどれか。",
    "選択肢": [
      "心配してはいけない",
      "心配する必要はない",
      "心配するはずがない"
    ],
    "正解": 2,
    "解説": "助動詞の need not は「〜する必要はない」。禁止 must not（してはいけない）とは意味が異なる。"
  },
  {
    "問題文": "I cannot but admire his courage. この cannot but の意味として最も適切なものはどれか。",
    "選択肢": [
      "賞賛することができない",
      "賞賛すべきではない",
      "賞賛せずにはいられない"
    ],
    "正解": 3,
    "解説": "cannot but + 原形は「〜せずにはいられない」。cannot help -ing と同義で、不可能や禁止の意味ではない。"
  },
  {
    "問題文": "It is necessary that he ___ present at the meeting. 空所に最も適切な形はどれか。",
    "選択肢": [
      "be",
      "is",
      "was"
    ],
    "正解": 1,
    "解説": "necessary / require / suggest などに続く that 節は (should) + 原形で、should が省略されると動詞は原形 be になる。"
  },
  {
    "問題文": "It may be expensive, but it is worth buying. この may の働きとして最も適切なものはどれか。",
    "選択肢": [
      "許可を表す",
      "譲歩を表す（確かに〜だが）",
      "能力を表す"
    ],
    "正解": 2,
    "解説": "may ..., but ... の形の may は「確かに〜かもしれないが」という譲歩を表す。許可や能力の用法ではない。"
  },
  {
    "問題文": "Accidents will happen no matter how careful we are. この will の意味として最も適切なものはどれか。",
    "選択肢": [
      "これから起こるだろうという予測",
      "起こってもよいという許可",
      "（よく）起こるものだという習性"
    ],
    "正解": 3,
    "解説": "一般的な性質・習性を述べる will は「〜するものだ」。未来の予測ではなく、ことわざ的な傾向を表す。"
  },
  {
    "問題文": "Shall I open the window for you? この文の意味として最も適切なものはどれか。",
    "選択肢": [
      "窓を開けましょうか",
      "窓を開けねばならない",
      "窓を開けるだろう"
    ],
    "正解": 1,
    "解説": "Shall I ...? は「（私が）〜しましょうか」という申し出。義務や単純未来ではなく、相手の意向を尋ねる表現。"
  },
  {
    "問題文": "I couldn't help laughing at his joke. この couldn't help -ing の意味として最も適切なものはどれか。",
    "選択肢": [
      "笑うのを手伝えなかった",
      "笑わずにはいられなかった",
      "笑ってはいけなかった"
    ],
    "正解": 2,
    "解説": "cannot help -ing は「〜せずにはいられない」。help を「手伝う」と直訳せず、「避ける」の意味で押さえる。"
  },
  {
    "問題文": "He ought to have checked the data before publishing. この ought to have checked の意味として最も適切なものはどれか。",
    "選択肢": [
      "確認したにちがいない",
      "確認する必要はなかった",
      "確認すべきだった（のにしなかった）"
    ],
    "正解": 3,
    "解説": "ought to have p.p. は should have p.p. と同様、「〜すべきだったのに（しなかった）」という非難・後悔を表す。"
  }
]
